netbox_kafka_producer/__init__.py
netbox_kafka_producer/middleware.py
netbox_kafka_producer-1.0.22.dist-info/LICENSE
netbox_kafka_producer-1.0.22.dist-info/METADATA
netbox_kafka_producer-1.0.22.dist-info/WHEEL
netbox_kafka_producer-1.0.22.dist-info/top_level.txt
netbox_kafka_producer-1.0.22.dist-info/RECORD
