Metadata-Version: 2.1
Name: netbox-kafka-producer
Version: 1.0.22
Summary: Easily publish NetBox changes to Kafka
Home-page: https://github.com/ebusto/netbox-kafka-producer
Author: Eric Busto
Author-email: ebusto@nvidia.com
License: UNKNOWN
Platform: UNKNOWN
Classifier: Environment :: Web Environment
Classifier: Framework :: Django
Classifier: Intended Audience :: Developers
Classifier: License :: OSI Approved :: MIT License
Classifier: Operating System :: OS Independent
Classifier: Programming Language :: Python :: 3
License-File: LICENSE
Requires-Dist: confluent-kafka (==1.7.0)
Requires-Dist: dictdiffer (==0.9.0)
